realtimex_services_api/__init__.py
realtimex_services_api/cli.py
realtimex_services_api/main.py
realtimex_services_api/modules/__init__.py
realtimex_services_api/modules/a2a_agents/__init__.py
realtimex_services_api/modules/a2a_agents/api.py
realtimex_services_api/modules/agent_flows/__init__.py
realtimex_services_api/modules/agent_flows/api.py
realtimex_services_api/modules/agent_flows/dependencies.py
realtimex_services_api/modules/agent_flows/exceptions.py
realtimex_services_api/modules/agent_flows/schemas.py
realtimex_services_api/modules/agent_flows/service.py
realtimex_services_api/modules/agent_flows/utils/__init__.py
realtimex_services_api/modules/agent_flows/utils/flow_processing.py
realtimex_services_api/modules/agent_flows/utils/streaming.py
realtimex_services_api/modules/python_interpreter/__init__.py
realtimex_services_api/modules/python_interpreter/api.py
realtimex_services_api/telemetry/__init__.py
realtimex_services_api/telemetry/tracing.py
realtimex_services_api/utils.py
realtimex_services_api-0.1.6.dist-info/WHEEL
realtimex_services_api-0.1.6.dist-info/entry_points.txt
realtimex_services_api-0.1.6.dist-info/METADATA
realtimex_services_api-0.1.6.dist-info/RECORD
