Metadata-Version: 2.3
Name: realtimex-services-api
Version: 0.1.6
Summary: Add your description here
Author: rta_phuongnguyen
Author-email: rta_phuongnguyen <phuongnguyen@rtanalytics.vn>
Requires-Dist: fastapi
Requires-Dist: uvicorn
Requires-Dist: realtimex-agent-flows-mcp-server
Requires-Dist: dotenv
Requires-Dist: realtimex-agent-flows-builder
Requires-Dist: realtimex-agent-a2a-agent
Requires-Dist: arize-phoenix-otel
Requires-Dist: openinference-instrumentation-langchain
Requires-Dist: openinference-instrumentation-mcp
Requires-Dist: litellm==1.77.1
Requires-Python: >=3.11
